pytickersymbols/__init__.py
pytickersymbols/indices_data.py
pytickersymbols-1.17.7.dist-info/METADATA
pytickersymbols-1.17.7.dist-info/WHEEL
pytickersymbols-1.17.7.dist-info/licenses/LICENSE
pytickersymbols-1.17.7.dist-info/RECORD
