Metadata-Version: 2.4
Name: pytickersymbols
Version: 1.17.7
Summary: pytickersymbols provides access to google and yahoo ticker symbols
License: MIT
License-File: LICENSE
Author: SlashGordon
Author-email: slash.gordon.dev@gmail.com
Requires-Python: >=3.11,<4.0
Classifier: License :: OSI Approved :: MIT License
Classifier: Programming Language :: Python :: 3
Classifier: Programming Language :: Python :: 3.11
Classifier: Programming Language :: Python :: 3.12
Classifier: Programming Language :: Python :: 3.13
Classifier: Programming Language :: Python :: 3.14
Requires-Dist: beautifulsoup4 (>=4.12.0,<5.0.0)
Requires-Dist: requests (>=2.31.0,<3.0.0)
